allure_pytest_bdd/__init__.py
allure_pytest_bdd/plugin.py
allure_pytest_bdd/pytest_bdd_listener.py
allure_pytest_bdd/utils.py
allure_pytest_bdd_temp_fix-2.9.46.dist-info/METADATA
allure_pytest_bdd_temp_fix-2.9.46.dist-info/WHEEL
allure_pytest_bdd_temp_fix-2.9.46.dist-info/entry_points.txt
allure_pytest_bdd_temp_fix-2.9.46.dist-info/top_level.txt
allure_pytest_bdd_temp_fix-2.9.46.dist-info/RECORD
