Metadata-Version: 2.1
Name: allure-pytest-bdd-temp-fix
Version: 2.9.46
Summary: Temporary repo till PR is merged #660
Home-page: https://github.com/a-bezkrovnyi/allure-python-temp
Author: QAMetaSoftware, Stanislav Seliverstov
Author-email: sseliverstov@qameta.io
License: Apache-2.0
Keywords: allure reporting pytest
Platform: UNKNOWN
Classifier: Development Status :: 5 - Production/Stable
Classifier: Framework :: Pytest
Classifier: Intended Audience :: Developers
Classifier: License :: OSI Approved :: Apache Software License
Classifier: Topic :: Software Development :: Quality Assurance
Classifier: Topic :: Software Development :: Testing
Classifier: Programming Language :: Python :: 3
Classifier: Programming Language :: Python :: 3 :: Only
Requires-Dist: pytest (>=4.5.0)
Requires-Dist: pytest-bdd (>=5.0.0)
Requires-Dist: six (>=1.9.0)
Requires-Dist: allure-python-commons-temp-fix (==2.9.46)
